Starforge/__init__.py
Starforge/astronomy.py
Starforge/cli.py
Starforge/core.py
Starforge/renderer.py
Starforge/utils.py
py_starforge-1.0.3.dist-info/licenses/LICENSE
py_starforge-1.0.3.dist-info/METADATA
py_starforge-1.0.3.dist-info/WHEEL
py_starforge-1.0.3.dist-info/entry_points.txt
py_starforge-1.0.3.dist-info/top_level.txt
py_starforge-1.0.3.dist-info/RECORD
