Metadata-Version: 2.4
Name: py-starforge
Version: 1.0.3
Summary: A Python library for generating beautiful, accurate astronomical star charts
Author-email: Aditya Gaur <adityagaur.home@gmail.com>
Maintainer-email: Aditya Gaur <adityagaur.home@gmail.com>
License: MIT
Project-URL: Homepage, https://github.com/xdityagr/ProjectStarForge
Project-URL: Documentation, https://github.com/xdityagr/ProjectStarForge#readme
Project-URL: Repository, https://github.com/xdityagr/ProjectStarForge.git
Project-URL: Issues, https://github.com/xdityagr/ProjectStarForge/issues
Project-URL: Changelog, https://github.com/xdityagr/ProjectStarForge/releases
Keywords: astronomy,star chart,starmap,constellation,celestial,svg,visualization,skyfield,stars,night sky
Classifier: Development Status :: 4 - Beta
Classifier: Intended Audience :: Developers
Classifier: Intended Audience :: Science/Research
Classifier: Intended Audience :: Education
Classifier: License :: OSI Approved :: MIT License
Classifier: Operating System :: OS Independent
Classifier: Programming Language :: Python :: 3
Classifier: Programming Language :: Python :: 3.8
Classifier: Programming Language :: Python :: 3.9
Classifier: Programming Language :: Python :: 3.10
Classifier: Programming Language :: Python :: 3.11
Classifier: Programming Language :: Python :: 3.12
Classifier: Topic :: Scientific/Engineering :: Astronomy
Classifier: Topic :: Scientific/Engineering :: Visualization
Classifier: Topic :: Multimedia :: Graphics
Requires-Python: >=3.8
License-File: LICENSE
Requires-Dist: skyfield>=1.45
Requires-Dist: svgwrite>=1.4
Requires-Dist: geonamescache>=1.6
Requires-Dist: colorama>=0.4
Requires-Dist: pytz>=2023.0
Requires-Dist: pandas>=2.0.0
Provides-Extra: dev
Requires-Dist: pytest>=7.0; extra == "dev"
Requires-Dist: pytest-cov>=4.0; extra == "dev"
Requires-Dist: black>=23.0; extra == "dev"
Requires-Dist: ruff>=0.1; extra == "dev"
Provides-Extra: export
Requires-Dist: cairosvg>=2.7; extra == "export"
Requires-Dist: Pillow>=10.0; extra == "export"
Dynamic: license-file
